libsnmp/__init__.py
libsnmp/asynrole.py
libsnmp/debug.py
libsnmp/rfc1155.py
libsnmp/rfc1157.py
libsnmp/rfc1902.py
libsnmp/rfc1905.py
libsnmp/role.py
libsnmp/snmpmanager.py
libsnmp/util.py
libsnmp/v1.py
libsnmp/v2.py
libsnmp-3.0.1.dist-info/METADATA
libsnmp-3.0.1.dist-info/WHEEL
libsnmp-3.0.1.dist-info/licenses/LICENSE
libsnmp-3.0.1.dist-info/RECORD
