Metadata-Version: 2.1
Name: libsnmp
Version: 3.0.1
Summary: A pure Python implementation of the Simple Network Management Protocol
Project-URL: homepage, https://github.com/jpwarren/libsnmp
Project-URL: documentation, https://github.com/jpwarren/libsnmp
Project-URL: repository, https://github.com/jpwarren/libsnmp
Author: Justin Warren
Author-email: daedalus@eigenmagic.com
License: Copyright (c) 2003 Justin Warren <daedalus@eigenmagic.com>
License-File: LICENSE
Keywords: SNMP,library
Classifier: Development Status :: 5 - Production/Stable
Classifier: Intended Audience :: Developers
Classifier: License :: OSI Approved :: MIT License
Classifier: Natural Language :: English
Classifier: Operating System :: OS Independent
Classifier: Programming Language :: Python :: 3
Classifier: Topic :: Communications
Classifier: Topic :: Internet
Classifier: Topic :: System :: Monitoring
Classifier: Topic :: System :: Networking :: Monitoring
Requires-Python: >=3.0
